lux/__init__.py
lux/_version.py
lux/action/__init__.py
lux/action/column_group.py
lux/action/correlation.py
lux/action/custom.py
lux/action/enhance.py
lux/action/filter.py
lux/action/generalize.py
lux/action/row_group.py
lux/action/similarity.py
lux/action/univariate.py
lux/core/__init__.py
lux/core/frame.py
lux/core/series.py
lux/executor/Executor.py
lux/executor/PandasExecutor.py
lux/executor/SQLExecutor.py
lux/executor/__init__.py
lux/history/__init__.py
lux/history/event.py
lux/history/history.py
lux/interestingness/__init__.py
lux/interestingness/interestingness.py
lux/processor/Compiler.py
lux/processor/Parser.py
lux/processor/Validator.py
lux/processor/__init__.py
lux/utils/__init__.py
lux/utils/date_utils.py
lux/utils/message.py
lux/utils/utils.py
lux/vis/Clause.py
lux/vis/Vis.py
lux/vis/VisList.py
lux/vis/__init__.py
lux/vislib/__init__.py
lux/vislib/altair/AltairChart.py
lux/vislib/altair/AltairRenderer.py
lux/vislib/altair/BarChart.py
lux/vislib/altair/Heatmap.py
lux/vislib/altair/Histogram.py
lux/vislib/altair/LineChart.py
lux/vislib/altair/ScatterChart.py
lux/vislib/altair/__init__.py
tests/__init__.py
tests/context.py
tests/test_action.py
tests/test_compiler.py
tests/test_dates.py
tests/test_display.py
tests/test_error_warning.py
tests/test_executor.py
tests/test_interestingness.py
tests/test_maintainence.py
tests/test_nan.py
tests/test_pandas.py
tests/test_pandas_coverage.py
tests/test_parser.py
tests/test_performance.py
tests/test_type.py
tests/test_vis.py
lux_api-0.2.0.dist-info/LICENSE
lux_api-0.2.0.dist-info/METADATA
lux_api-0.2.0.dist-info/WHEEL
lux_api-0.2.0.dist-info/top_level.txt
lux_api-0.2.0.dist-info/RECORD
