Metadata-Version: 2.1
Name: lux-api
Version: 0.2.0
Summary: A Python API for Intelligent Data Discovery
Home-page: https://github.com/lux-org/lux
Author: Doris Jung-Lin Lee
Author-email: dorisjunglinlee@gmail.com
License: Apache-2.0 License
Keywords: Visualization,Analytics,Data Science,Data Analysis
Platform: UNKNOWN
Classifier: Development Status :: 1 - Planning
Classifier: Intended Audience :: Developers
Classifier: Intended Audience :: Science/Research
Classifier: Intended Audience :: Other Audience
Classifier: Topic :: Scientific/Engineering :: Information Analysis
Classifier: Topic :: Scientific/Engineering :: Visualization
Classifier: License :: OSI Approved :: Apache Software License
Classifier: Programming Language :: Python :: 3
Requires-Python: >=3.5
Requires-Dist: scipy (>=1.3.3)
Requires-Dist: altair (>=4.0.0)
Requires-Dist: jupyter
Requires-Dist: vega-datasets
Requires-Dist: pandas (>=1.1.0)
Requires-Dist: pytest (>=5.3.1)
Requires-Dist: pytest-cov (>=2.8.1)
Requires-Dist: scikit-learn (>=0.22)
Requires-Dist: Sphinx (>=3.0.2)
Requires-Dist: sphinx-rtd-theme (>=0.4.3)
Requires-Dist: lux-widget
Provides-Extra: test
Requires-Dist: pytest ; extra == 'test'
